oxl_utils/__init__.py
oxl_utils/debug.py
oxl_utils/dt.py
oxl_utils/log.py
oxl_utils/net.py
oxl_utils/net_test.py
oxl_utils/ps.py
oxl_utils/ps_test.py
oxl_utils/state.py
oxl_utils/state_test.py
oxl_utils/crypto/__init__.py
oxl_utils/crypto/aes_cbc.py
oxl_utils/crypto/aes_cbc_test.py
oxl_utils/dj/__init__.py
oxl_utils/dj/dt.py
oxl_utils/dj/model.py
oxl_utils/valid/__init__.py
oxl_utils/valid/base.py
oxl_utils/valid/dns.py
oxl_utils/valid/dns_test.py
oxl_utils/valid/email.py
oxl_utils/valid/email_test.py
oxl_utils/valid/net.py
oxl_utils/valid/net_test.py
oxl_utils/valid/uuid.py
oxl_utils/valid/uuid_test.py
oxl_utils-0.3.dist-info/LICENSE.txt
oxl_utils-0.3.dist-info/METADATA
oxl_utils-0.3.dist-info/WHEEL
oxl_utils-0.3.dist-info/top_level.txt
oxl_utils-0.3.dist-info/RECORD
