Metadata-Version: 2.1
Name: oxl-utils
Version: 0.3
Summary: OXL Utils-Collecion
Author-email: Rath Pascal <contact@oxl.at>
License: GNU GENERAL PUBLIC LICENSE
Project-URL: Homepage, https://www.oxl.at
Project-URL: Documentation, https://github.com/O-X-L/py-utils
Project-URL: Repository, https://github.com/O-X-L/py-utils.git
Project-URL: Issues, https://github.com/O-X-L/py-utils/issues
Keywords: utils,validators,django
Classifier: Programming Language :: Python :: 3
Classifier: License :: OSI Approved :: GNU General Public License v3 (GPLv3)
Requires-Python: >=3.10
License-File: LICENSE.txt
Requires-Dist: pytz
Requires-Dist: dnspython
Requires-Dist: pycryptodome
